PdmModule/PdMApi.py
PdmModule/__init__.py
PdmModule/example.py
PdmModule/example2.py
PdmModule/Handlers/__init__.py
PdmModule/Handlers/pairdetectionHandler.py
PdmModule/Handlers/xgboostPairHandler.py
PdmModule/Models/__init__.py
PdmModule/Models/pairdetection.py
PdmModule/Models/xgboostPerFeature.py
PdmModule/thresholding/__init__.py
PdmModule/thresholding/thresholding.py
PdmModule/utils/__init__.py
PdmModule/utils/dbcontector.py
PdmModule/utils/distances.py
PdmModule/utils/structure.py
pdmmodule-0.1.2.dist-info/METADATA
pdmmodule-0.1.2.dist-info/WHEEL
pdmmodule-0.1.2.dist-info/licenses/LICENSE
pdmmodule-0.1.2.dist-info/RECORD
